python_utils/__about__.py
python_utils/__init__.py
python_utils/aio.py
python_utils/containers.py
python_utils/converters.py
python_utils/decorators.py
python_utils/exceptions.py
python_utils/formatters.py
python_utils/generators.py
python_utils/import_.py
python_utils/logger.py
python_utils/loguru.py
python_utils/py.typed
python_utils/terminal.py
python_utils/time.py
python_utils/types.py
python_utils-3.9.0.dist-info/LICENSE
python_utils-3.9.0.dist-info/METADATA
python_utils-3.9.0.dist-info/WHEEL
python_utils-3.9.0.dist-info/top_level.txt
python_utils-3.9.0.dist-info/RECORD
