Metadata-Version: 2.1
Name: python-utils
Version: 3.9.0
Summary: Python Utils is a module with some convenient utilities not included with the standard Python install
Home-page: https://github.com/WoLpH/python-utils
Author: Rick van Hattem
Author-email: Wolph@wol.ph
License: BSD
Classifier: License :: OSI Approved :: BSD License
Requires-Python: >3.9.0
License-File: LICENSE
Requires-Dist: typing_extensions>3.10.0.2
Provides-Extra: loguru
Requires-Dist: loguru; extra == "loguru"
Provides-Extra: docs
Requires-Dist: mock; extra == "docs"
Requires-Dist: sphinx; extra == "docs"
Requires-Dist: python-utils; extra == "docs"
Provides-Extra: tests
Requires-Dist: ruff; extra == "tests"
Requires-Dist: pyright; extra == "tests"
Requires-Dist: pytest; extra == "tests"
Requires-Dist: pytest-cov; extra == "tests"
Requires-Dist: pytest-mypy; extra == "tests"
Requires-Dist: pytest-asyncio; extra == "tests"
Requires-Dist: sphinx; extra == "tests"
Requires-Dist: types-setuptools; extra == "tests"
Requires-Dist: loguru; extra == "tests"
Requires-Dist: loguru-mypy; extra == "tests"
Requires-Dist: mypy-ipython; extra == "tests"
Requires-Dist: blessings; extra == "tests"
